{
  "meta": {
    "page": 144,
    "first_line": "ke jabi ke jabi bhāi bhava-sindhu pāra"
  },
  "title": [
    "Ke jabi ke jabi"
  ],
  "author": [
    "by Śrīla Lochan Dās Ṭhākur"
  ],
  "verses": [
    {
      "number": "1",
      "text": [
        "ke jabi ke jabi bhāi bhava-sindhu pāra",
        "dhanya kali-yuge re chaitanya avatāra"
      ],
      "translation": [
        "Who will go, oh brother, who will go to cross the ocean of material existence? The wealth and great fortune of this age of Kali is the incarnation of Lord Chaitanya."
      ]
    },
    {
      "number": "2",
      "text": [
        "āmāra gaurāṅgera ghāṭe ujānakheyā boy",
        "kaḍipāti nāhi lāge amani pāra hoy"
      ],
      "translation": [
        "My Lord Gaurāṅga stands at the jetty ready to ferry his servants upstream across this material existence. For no charge he is immediately taking them."
      ]
    },
    {
      "number": "3",
      "text": [
        "harināmera tarīkhāni śrī-guru-kāṇḍārī",
        "saṅkīrtana-keroyāla du’bahu pasāri"
      ],
      "translation": [
        "The ferry-boat is the Holy Names of the Lord and the spiritual master is the captain. The oars are the outstretched arms in the *saṅkīrtan*."
      ]
    },
    {
      "number": "4",
      "text": [
        "sarva-jīva uddhāra hoilo premera bātāse",
        "lochana paḍiyā roilo karamera doṣe"
      ],
      "translation": [
        "The favourable wind is divine love for Lord Krishna and all the fallen souls have been rescued on this boat. Only Lochan Dās is left behind due to the faults of his own misdeeds."
      ]
    }
  ]
}